<keymap version="1" name="macOS copy" parent="Mac OS X 10.5+">
  <action id="ActivateBookmarksToolWindow" />
  <action id="ActivateFavoritesToolWindow" />
  <action id="ActivateProjectToolWindow" />
  <action id="Back">
    <keyboard-shortcut first-keystroke="meta left" />
  </action>
  <action id="ChangesView.Move" />
  <action id="ChangesView.SetDefault" />
  <action id="ClassNameCompletion" />
  <action id="CodeCompletion">
    <keyboard-shortcut first-keystroke="meta slash" />
  </action>
  <action id="CommentByBlockComment">
    <keyboard-shortcut first-keystroke="shift ctrl slash" />
  </action>
  <action id="CommentByLineComment">
    <keyboard-shortcut first-keystroke="ctrl slash" />
  </action>
  <action id="CompareTwoFiles" />
  <action id="CompileDirty">
    <keyboard-shortcut first-keystroke="meta b" />
  </action>
  <action id="Console.TableResult.NavigateForeignAction">
    <mouse-shortcut keystroke="meta button1" />
    <mouse-shortcut keystroke="Force touch" />
    <mouse-shortcut keystroke="button2" />
  </action>
  <action id="CopyElement" />
  <action id="DatabaseView.PropertiesAction" />
  <action id="Debugger.AddToWatch">
    <keyboard-shortcut first-keystroke="meta f4" />
  </action>
  <action id="Diff.ShowDiff" />
  <action id="DuplicatesForm.SendToLeft" />
  <action id="DuplicatesForm.SendToRight" />
  <action id="EditSource">
    <keyboard-shortcut first-keystroke="f3" />
  </action>
  <action id="EditorDeleteLine">
    <keyboard-shortcut first-keystroke="meta d" />
  </action>
  <action id="EditorDuplicate">
    <keyboard-shortcut first-keystroke="meta down" />
  </action>
  <action id="EditorLineEnd">
    <keyboard-shortcut first-keystroke="end" />
    <keyboard-shortcut first-keystroke="ctrl e" />
  </action>
  <action id="EditorLineStart">
    <keyboard-shortcut first-keystroke="home" />
    <keyboard-shortcut first-keystroke="ctrl a" />
  </action>
  <action id="EditorToggleCase">
    <keyboard-shortcut first-keystroke="shift ctrl u" />
  </action>
  <action id="EvaluateExpression">
    <keyboard-shortcut first-keystroke="f5" />
  </action>
  <action id="FileChooser.GotoDesktop" />
  <action id="FileChooser.GotoHome" />
  <action id="FileChooser.GotoProject" />
  <action id="FileStructurePopup">
    <keyboard-shortcut first-keystroke="meta s" />
  </action>
  <action id="FindPrevious" />
  <action id="FindUsages">
    <keyboard-shortcut first-keystroke="shift meta g" />
  </action>
  <action id="Forward">
    <keyboard-shortcut first-keystroke="meta right" />
  </action>
  <action id="Generate">
    <keyboard-shortcut first-keystroke="meta i" />
  </action>
  <action id="GoToRequestMapping">
    <keyboard-shortcut first-keystroke="meta back_slash" />
  </action>
  <action id="GotoAction" />
  <action id="GotoBookmark1" />
  <action id="GotoDeclaration">
    <mouse-shortcut keystroke="meta button1" />
    <mouse-shortcut keystroke="Force touch" />
    <mouse-shortcut keystroke="button2" />
  </action>
  <action id="GotoImplementation">
    <keyboard-shortcut first-keystroke="shift ctrl i" />
  </action>
  <action id="GotoUrlAction" />
  <action id="Graph.ActualSize">
    <keyboard-shortcut first-keystroke="meta divide" />
  </action>
  <action id="Graph.RouteEdges" />
  <action id="GuiDesigner.Duplicate" />
  <action id="Images.Editor.ActualSize">
    <keyboard-shortcut first-keystroke="meta divide" />
  </action>
  <action id="Jdbc.OpenConsole.New" />
  <action id="NavBar-selectHome">
    <keyboard-shortcut first-keystroke="home" />
    <keyboard-shortcut first-keystroke="ctrl a" />
  </action>
  <action id="OptimizeImports">
    <keyboard-shortcut first-keystroke="shift ctrl o" />
  </action>
  <action id="PoToggleSelection" />
  <action id="QuickEvaluateExpression" />
  <action id="QuickJavaDoc">
    <keyboard-shortcut first-keystroke="f1" />
  </action>
  <action id="RecentLocations" />
  <action id="ReformatCode">
    <keyboard-shortcut first-keystroke="shift ctrl f" />
  </action>
  <action id="RenameElement">
    <keyboard-shortcut first-keystroke="meta 2" />
  </action>
  <action id="RevealIn">
    <keyboard-shortcut first-keystroke="shift meta e" />
  </action>
  <action id="RunDashboard.CopyConfiguration" />
  <action id="RunToCursor">
    <keyboard-shortcut first-keystroke="meta f9" />
  </action>
  <action id="SaveAll" />
  <action id="SearchEverywhere.NavigateToNextGroup">
    <keyboard-shortcut first-keystroke="page_down" />
  </action>
  <action id="SendEOF" />
  <action id="ShowIntentionActions">
    <keyboard-shortcut first-keystroke="meta 1" />
  </action>
  <action id="ShowReformatFileDialog" />
  <action id="SmartTypeCompletion" />
  <action id="StringManipulation.ToDotStyleAction">
    <keyboard-shortcut first-keystroke="shift ctrl period" />
  </action>
  <action id="StringManipulation.ToSnakeCaseOrCamelCase">
    <keyboard-shortcut first-keystroke="shift ctrl s" />
  </action>
  <action id="SurroundWith">
    <keyboard-shortcut first-keystroke="shift meta s" />
  </action>
  <action id="ToggleBookmark" />
  <action id="Vcs.MoveChangedLinesToChangelist" />
  <action id="XDebugger.CopyWatch" />
  <action id="XDebugger.RemoveAllWatches">
    <keyboard-shortcut first-keystroke="shift meta p" />
  </action>
  <action id="openAssertEqualsDiff" />
</keymap>